{
  "name": "True Black",
  "description": "Creatures of the night",
  "authors": [
      {
          "name": "fero",
          "id": "924621655345627196"
      }
  ],
  "semanticColors": {
      "BACKGROUND_PRIMARY": [
          "#000000"
      ],
      "BACKGROUND_SECONDARY": [
          "#000000"
      ],
      "BACKGROUND_SECONDARY_ALT": [
          "#000000"
      ],
      "BACKGROUND_TERTIARY": [
          "#000000"
      ],
      "BACKGROUND_ACCENT": [
          "#000000"
      ],
      "BACKGROUND_FLOATING": [
          "#000000"
      ],
      "BACKGROUND_NESTED_FLOATING": [
          "#000000"
      ],
      "BACKGROUND_MOBILE_PRIMARY": [
          "#000000"
      ],
      "BACKGROUND_MOBILE_SECONDARY": [
          "#000000"
      ],
      "BACKGROUND_MODIFIER_ACTIVE": [
          "#000000"
      ],
      "BACKGROUND_MODIFIER_SELECTED": [
          "#000000"
      ],
      "BACKGROUND_MESSAGE_HIGHLIGHT": [
        "#000000"
      ],
      "CHAT_BACKGROUND": [
          "#000000"
      ],
      "CHANNELS_DEFAULT": [
          "#c2c2c2"
      ],
      "HEADER_PRIMARY": [
          "#ffffff"
      ],
      "HEADER_SECONDARY": [
          "#c2c2c2"
      ],
      "INTERACTIVE_ACTIVE": [
          "#ffffff"
      ],
      "INTERACTIVE_NORMAL": [
          "#d0d1d4"
      ],
      "TEXT_MUTED": [
          "#c2c2c2"
      ]
  },
  "rawColors": {
    "PRIMARY_100": "#C2C2C2",
    "PRIMARY_300": "#C2C2C2",
    "PRIMARY_360": "#FFFFFF",
    "PRIMARY_500": "#000000",
    "PRIMARY_510": "#000000",
    "PRIMARY_520": "#000000",
    "PRIMARY_530": "#000000",
    "PRIMARY_540": "#000000",
    "PRIMARY_550": "#000000",
    "PRIMARY_560": "#000000",
    "PRIMARY_570": "#000000",
    "PRIMARY_580": "#000000",
    "PRIMARY_590": "#000000",
    "PRIMARY_600": "#000000",
    "PRIMARY_610": "#000000",
    "PRIMARY_620": "#000000",
    "PRIMARY_630": "#000000",
    "PRIMARY_640": "#000000",
    "PRIMARY_650": "#000000",
    "PRIMARY_660": "#000000",
    "PRIMARY_670": "#000000",
    "PRIMARY_680": "#000000",
    "PRIMARY_690": "#000000",
    "PRIMARY_700": "#000000",
    "PRIMARY_710": "#000000",
    "PRIMARY_720": "#000000",
    "PRIMARY_730": "#000000",
    "PRIMARY_740": "#000000",
    "PRIMARY_750": "#000000",
    "PRIMARY_760": "#000000",
    "PRIMARY_770": "#000000",
    "PRIMARY_780": "#000000",
    "PRIMARY_790": "#000000",
    "PRIMARY_800": "#000000",
    "PRIMARY_810": "#000000",
    "PRIMARY_820": "#000000",
    "PRIMARY_830": "#000000",
    "PRIMARY_840": "#000000",
    "PRIMARY_850": "#000000",
    "PRIMARY_860": "#000000",
    "PRIMARY_870": "#000000",
    "PRIMARY_880": "#000000",
    "PRIMARY_890": "#000000",
    "PRIMARY_900": "#000000",
    "PRIMARY_905": "#000000",
    "PRIMARY_910": "#000000",
    "PRIMARY_915": "#000000",
    "PRIMARY_920": "#000000",
    "PRIMARY_925": "#000000"
  },
  "spec": 2
}
